dffml_operations_binsec/__init__.py
dffml_operations_binsec/definitions.py
dffml_operations_binsec/log.py
dffml_operations_binsec/operations.py
dffml_operations_binsec/version.py
tests/__init__.py
tests/test_operations.py
dffml_operations_binsec-0.1.0.post0.dist-info/LICENSE
dffml_operations_binsec-0.1.0.post0.dist-info/METADATA
dffml_operations_binsec-0.1.0.post0.dist-info/WHEEL
dffml_operations_binsec-0.1.0.post0.dist-info/entry_points.txt
dffml_operations_binsec-0.1.0.post0.dist-info/top_level.txt
dffml_operations_binsec-0.1.0.post0.dist-info/RECORD
